toolformer/__init__.py
toolformer/_modidx.py
toolformer/api.py
toolformer/data_generator.py
toolformer/model.py
toolformer/prompt.py
toolformer/utils.py
toolformer-0.0.4.dist-info/LICENSE
toolformer-0.0.4.dist-info/METADATA
toolformer-0.0.4.dist-info/WHEEL
toolformer-0.0.4.dist-info/entry_points.txt
toolformer-0.0.4.dist-info/top_level.txt
toolformer-0.0.4.dist-info/RECORD
