Metadata-Version: 2.1
Name: toolformer
Version: 0.0.4
Summary: Implementation of Toolformer
Home-page: https://github.com/xrsrke/toolformer
Author: xrsrke
Author-email: xariusdrake@hotmail.com
License: Apache Software License 2.0
Keywords: nbdev jupyter notebook python
Classifier: Development Status :: 4 - Beta
Classifier: Intended Audience :: Developers
Classifier: Natural Language :: English
Classifier: Programming Language :: Python :: 3.7
Classifier: Programming Language :: Python :: 3.8
Classifier: Programming Language :: Python :: 3.9
Classifier: Programming Language :: Python :: 3.10
Classifier: License :: OSI Approved :: Apache Software License
Requires-Python: >=3.7
License-File: LICENSE
Requires-Dist: torch
Requires-Dist: einops
Requires-Dist: torchtyping
Requires-Dist: langchain
Requires-Dist: transformers
Requires-Dist: datasets
Requires-Dist: wolframalpha
Provides-Extra: dev
Requires-Dist: pytest ; extra == 'dev'
